setup.py
rda_enhancement/__init__.py
rda_enhancement/base_converter.py
rda_enhancement/pcc_conversion.py
rda_enhancement/tests.py
rda_enhancement.egg-info/PKG-INFO
rda_enhancement.egg-info/SOURCES.txt
rda_enhancement.egg-info/dependency_links.txt
rda_enhancement.egg-info/not-zip-safe
rda_enhancement.egg-info/requires.txt
rda_enhancement.egg-info/top_level.txt