Metadata-Version: 1.1
Name: rda-enhancement
Version: 0.0.3
Summary: Library for RDA enhancing of Tutt Library MARC21 records
Home-page: https://github.com/Tutt-Library/rda-enhancement
Author: Jeremy Nelson
Author-email: jeremy.nelson@coloradocollege.edu
License: MIT License
Platform: any
Classifier: Intended Audience :: Developers
Classifier: License :: OSI Approved :: MIT License
Classifier: Operating System :: OS Independent
Classifier: Programming Language :: Python
Classifier: Programming Language :: Python :: 2.7
Classifier: Programming Language :: Python :: 3.4
Classifier: Topic :: Software Development :: Libraries :: Python Modules
